[
  {
    "id" : "31131d82-6c92-4b20-bb1e-73847d781391",
    "prId" : 3795,
    "comments" : [
      {
        "id" : "d79f8613-124d-43b7-9a11-60358f39cb2d",
        "parentId" : null,
        "author" : {
          "login" : "cocreature",
          "name" : "Moritz Kiefer",
          "avatarUrl" : "https://avatars1.githubusercontent.com/u/1313584?u=7864421488a876940b33e865c4b0091925617ca7&v=4"
        },
        "body" : "please bump this to the new commit after you merge your hlint PR.",
        "createdAt" : "2019-12-10T07:21:12Z",
        "updatedAt" : "2019-12-10T11:48:31Z",
        "lastEditedBy" : {
          "login" : "cocreature",
          "name" : "Moritz Kiefer",
          "avatarUrl" : "https://avatars1.githubusercontent.com/u/1313584?u=7864421488a876940b33e865c4b0091925617ca7&v=4"
        },
        "tags" : [
        ]
      },
      {
        "id" : "cd63d72a-b26a-4cde-b330-6d27611df898",
        "parentId" : "d79f8613-124d-43b7-9a11-60358f39cb2d",
        "author" : null,
        "body" : "Yes",
        "createdAt" : "2019-12-10T11:43:35Z",
        "updatedAt" : "2019-12-10T11:48:31Z",
        "lastEditedBy" : null,
        "tags" : [
        ]
      }
    ],
    "commit" : "94eaa0caa2c659b5aabcea0d36a851681ce58f93",
    "line" : 7,
    "diffHunk" : "@@ -5,9 +5,9 @@ packages:\n   - archive: http://digitalassetsdk.bintray.com/ghc-lib/ghc-lib-8.8.1.20191204.tar.gz\n     sha256: \"9648145ef7b3566fad7073ef63d0ef85056abe2c70c98f753306b70cbe9e0b5a\"\n   - github: digital-asset/hlint\n-    commit: \"951fdb6d28d7eed8ea1c7f3be69da29b61fcbe8f\"\n-    sha256: \"f5fb4cf98cde3ecf1209857208369a63ba21b04313d570c41dffe9f9139a1d34\"\n-    size: 167936\n+    commit: \"2eb1c457c28f0dae87ca9987f1a45e2b0ced6aae\""
  }
]