[
  {
    "id" : "c4f852f6-ce48-4bac-8c0e-1fe3416e874c",
    "prId" : 2178,
    "comments" : [
      {
        "id" : "1c1ef8f1-68db-4498-90d9-21771785b308",
        "parentId" : null,
        "author" : {
          "login" : "hurryabit",
          "name" : "Martin Huschenbett",
          "avatarUrl" : "https://avatars0.githubusercontent.com/u/11665611?u=7dbd00d5e7ea53919ed31dc4200f602ebca91c8f&v=4"
        },
        "body" : "What's the reasoning behind this change?",
        "createdAt" : "2019-07-17T08:15:00Z",
        "updatedAt" : "2019-07-30T22:55:02Z",
        "lastEditedBy" : {
          "login" : "hurryabit",
          "name" : "Martin Huschenbett",
          "avatarUrl" : "https://avatars0.githubusercontent.com/u/11665611?u=7dbd00d5e7ea53919ed31dc4200f602ebca91c8f&v=4"
        },
        "tags" : [
        ]
      },
      {
        "id" : "15956b79-5409-4f40-8488-2b3b7854b866",
        "parentId" : "1c1ef8f1-68db-4498-90d9-21771785b308",
        "author" : {
          "login" : "rohanjr",
          "name" : "Rohan Jacob-Rao",
          "avatarUrl" : "https://avatars1.githubusercontent.com/u/10836630?u=a30da7f2a9ceeb7c25249d5146f10fce61aeec4e&v=4"
        },
        "body" : "The goal was to export everything in `DA.Internal.Template`. Is there anything there we want to hide?",
        "createdAt" : "2019-07-18T19:04:08Z",
        "updatedAt" : "2019-07-30T22:55:02Z",
        "lastEditedBy" : {
          "login" : "rohanjr",
          "name" : "Rohan Jacob-Rao",
          "avatarUrl" : "https://avatars1.githubusercontent.com/u/10836630?u=a30da7f2a9ceeb7c25249d5146f10fce61aeec4e&v=4"
        },
        "tags" : [
        ]
      },
      {
        "id" : "811709fe-aa2a-4dde-b51f-beea7ff0ba0a",
        "parentId" : "1c1ef8f1-68db-4498-90d9-21771785b308",
        "author" : {
          "login" : "hurryabit",
          "name" : "Martin Huschenbett",
          "avatarUrl" : "https://avatars0.githubusercontent.com/u/11665611?u=7dbd00d5e7ea53919ed31dc4200f602ebca91c8f&v=4"
        },
        "body" : "Is there anything that was hidden before? If not, we can do it like you propose.",
        "createdAt" : "2019-07-19T07:25:06Z",
        "updatedAt" : "2019-07-30T22:55:02Z",
        "lastEditedBy" : {
          "login" : "hurryabit",
          "name" : "Martin Huschenbett",
          "avatarUrl" : "https://avatars0.githubusercontent.com/u/11665611?u=7dbd00d5e7ea53919ed31dc4200f602ebca91c8f&v=4"
        },
        "tags" : [
        ]
      },
      {
        "id" : "bd7e661e-68dd-4a02-92d2-6b8432794278",
        "parentId" : "1c1ef8f1-68db-4498-90d9-21771785b308",
        "author" : {
          "login" : "rohanjr",
          "name" : "Rohan Jacob-Rao",
          "avatarUrl" : "https://avatars1.githubusercontent.com/u/10836630?u=a30da7f2a9ceeb7c25249d5146f10fce61aeec4e&v=4"
        },
        "body" : "I think everything needs be exported now.",
        "createdAt" : "2019-07-19T12:52:05Z",
        "updatedAt" : "2019-07-30T22:55:02Z",
        "lastEditedBy" : {
          "login" : "rohanjr",
          "name" : "Rohan Jacob-Rao",
          "avatarUrl" : "https://avatars1.githubusercontent.com/u/10836630?u=a30da7f2a9ceeb7c25249d5146f10fce61aeec4e&v=4"
        },
        "tags" : [
        ]
      }
    ],
    "commit" : "ca591f5890a7d9487d0b2351de3d08b4592a1a87",
    "line" : 11,
    "diffHunk" : "@@ -1,1 +8,12 @@-- | Automatically imported qualified in every module.\nmodule DA.Internal.Desugar (\n    module DA.Internal.Template,\n    Eq(..), Show(..),\n    Bool(..), Text, Optional,"
  }
]