[
  {
    "id" : "8747d964-5ef4-421f-bf84-6b5f234def01",
    "prId" : 6846,
    "comments" : [
      {
        "id" : "3b2b329a-72ae-42a0-91bd-27c7b4001f57",
        "parentId" : null,
        "author" : {
          "login" : "gerolf-da",
          "name" : "Gerolf Seitz",
          "avatarUrl" : "https://avatars1.githubusercontent.com/u/29121423?u=f683aa614e742c653ae8c01b194905dcdef6e974&v=4"
        },
        "body" : "I don't think DAML on SQL should have support for seeding modes other than `strong`. Basically I don't see a reason for it even being an option.",
        "createdAt" : "2020-07-23T15:57:43Z",
        "updatedAt" : "2020-07-24T08:02:10Z",
        "lastEditedBy" : {
          "login" : "gerolf-da",
          "name" : "Gerolf Seitz",
          "avatarUrl" : "https://avatars1.githubusercontent.com/u/29121423?u=f683aa614e742c653ae8c01b194905dcdef6e974&v=4"
        },
        "tags" : [
          {
            "value" : "outdated"
          }
        ]
      },
      {
        "id" : "4a97e605-99a9-4db7-981b-d0d073980d96",
        "parentId" : "3b2b329a-72ae-42a0-91bd-27c7b4001f57",
        "author" : {
          "login" : "SamirTalwar-DA",
          "name" : "Samir Talwar",
          "avatarUrl" : "https://avatars2.githubusercontent.com/u/60356447?u=f6cdfccc6ea4254bd7c212099bbac2c27a00a28c&v=4"
        },
        "body" : "Two reasons.\r\n\r\n1. We use weak seeding in our conformance tests.\r\n2. Just like us, I expect users of DAML-on-SQL to run end-to-end tests. Perhaps lots of them, in parallel, with each one running against a fresh ledger. In this event, strong seeding might block, leading to timeouts that are very hard to diagnose.\r\n\r\nThere's a reason the option is called \"testing-weak\". It's for testing. 🙂 ",
        "createdAt" : "2020-07-23T16:15:54Z",
        "updatedAt" : "2020-07-24T08:02:10Z",
        "lastEditedBy" : {
          "login" : "SamirTalwar-DA",
          "name" : "Samir Talwar",
          "avatarUrl" : "https://avatars2.githubusercontent.com/u/60356447?u=f6cdfccc6ea4254bd7c212099bbac2c27a00a28c&v=4"
        },
        "tags" : [
          {
            "value" : "outdated"
          }
        ]
      },
      {
        "id" : "68116d2e-dc85-4a43-a756-7cb66a0f3711",
        "parentId" : "3b2b329a-72ae-42a0-91bd-27c7b4001f57",
        "author" : {
          "login" : "gerolf-da",
          "name" : "Gerolf Seitz",
          "avatarUrl" : "https://avatars1.githubusercontent.com/u/29121423?u=f683aa614e742c653ae8c01b194905dcdef6e974&v=4"
        },
        "body" : "Alright. Can I then still interest you in removing `testing-static`? This is really only useful for reproducible contract ids for demos or manuals.",
        "createdAt" : "2020-07-23T16:20:00Z",
        "updatedAt" : "2020-07-24T08:02:10Z",
        "lastEditedBy" : {
          "login" : "gerolf-da",
          "name" : "Gerolf Seitz",
          "avatarUrl" : "https://avatars1.githubusercontent.com/u/29121423?u=f683aa614e742c653ae8c01b194905dcdef6e974&v=4"
        },
        "tags" : [
          {
            "value" : "outdated"
          }
        ]
      },
      {
        "id" : "c7f6df81-7710-4545-89cd-fa839ee13bd7",
        "parentId" : "3b2b329a-72ae-42a0-91bd-27c7b4001f57",
        "author" : {
          "login" : "SamirTalwar-DA",
          "name" : "Samir Talwar",
          "avatarUrl" : "https://avatars2.githubusercontent.com/u/60356447?u=f6cdfccc6ea4254bd7c212099bbac2c27a00a28c&v=4"
        },
        "body" : "Sold! I also pulled out the common logic for seeding mode options.",
        "createdAt" : "2020-07-23T17:06:55Z",
        "updatedAt" : "2020-07-24T08:02:10Z",
        "lastEditedBy" : {
          "login" : "SamirTalwar-DA",
          "name" : "Samir Talwar",
          "avatarUrl" : "https://avatars2.githubusercontent.com/u/60356447?u=f6cdfccc6ea4254bd7c212099bbac2c27a00a28c&v=4"
        },
        "tags" : [
          {
            "value" : "outdated"
          }
        ]
      }
    ],
    "commit" : "b75808c6eefa20c168a80bec0a7a6bc8a077a03f",
    "line" : null,
    "diffHunk" : "@@ -0,0 +1,60 @@\n+// Copyright (c) 2020 Digital Asset (Switzerland) GmbH and/or its affiliates. All rights reserved.\n+// SPDX-License-Identifier: Apache-2.0\n+\n+package com.daml.on.sql\n+\n+import com.daml.ledger.participant.state.v1.SeedService.Seeding\n+import com.daml.platform.common.LedgerIdMode\n+import com.daml.platform.sandbox.cli.{CommonCli, SandboxCli}\n+import com.daml.platform.sandbox.config.SandboxConfig\n+import scopt.OptionParser\n+\n+private[sql] final class Cli(override val defaultConfig: SandboxConfig = DefaultConfig)\n+    extends SandboxCli {\n+\n+  private val seedingMap = Map[String, Option[Seeding]]("
  }
]