[
  {
    "id" : "effe95ae-bb7e-4731-84f5-54d63b602492",
    "prId" : 6619,
    "comments" : [
      {
        "id" : "4eb36416-e2d8-4363-b1d6-5bc3ce19b813",
        "parentId" : null,
        "author" : {
          "login" : "miklos-da",
          "name" : "Miklos",
          "avatarUrl" : "https://avatars0.githubusercontent.com/u/57664299?v=4"
        },
        "body" : "Having such a utility class is great for colored printing. However, I'd prefer something less intrusive via e.g. implicits, similar to the solution here:\r\nhttps://yobriefca.se/blog/2014/01/06/convenient-colouring-of-console-output-in-scala/\r\nThe only tweak that would be essential is adding a `$RESET` at the end of the printed text automatically so that you don't forget it (and everything will be printed in the color you postfix the string with). What do you think?",
        "createdAt" : "2020-07-06T14:11:19Z",
        "updatedAt" : "2020-07-06T14:35:48Z",
        "lastEditedBy" : {
          "login" : "miklos-da",
          "name" : "Miklos",
          "avatarUrl" : "https://avatars0.githubusercontent.com/u/57664299?v=4"
        },
        "tags" : [
          {
            "value" : "outdated"
          }
        ]
      },
      {
        "id" : "73233c7b-6c87-4e45-891e-6feae3aa4418",
        "parentId" : "4eb36416-e2d8-4363-b1d6-5bc3ce19b813",
        "author" : {
          "login" : "SamirTalwar-DA",
          "name" : "Samir Talwar",
          "avatarUrl" : "https://avatars2.githubusercontent.com/u/60356447?u=f6cdfccc6ea4254bd7c212099bbac2c27a00a28c&v=4"
        },
        "body" : "Sounds like a cool idea to me. I'll change it.",
        "createdAt" : "2020-07-06T14:29:47Z",
        "updatedAt" : "2020-07-06T14:35:48Z",
        "lastEditedBy" : {
          "login" : "SamirTalwar-DA",
          "name" : "Samir Talwar",
          "avatarUrl" : "https://avatars2.githubusercontent.com/u/60356447?u=f6cdfccc6ea4254bd7c212099bbac2c27a00a28c&v=4"
        },
        "tags" : [
          {
            "value" : "outdated"
          }
        ]
      },
      {
        "id" : "3d3bd28c-2fa9-49b2-a365-45a12f03d157",
        "parentId" : "4eb36416-e2d8-4363-b1d6-5bc3ce19b813",
        "author" : {
          "login" : "SamirTalwar-DA",
          "name" : "Samir Talwar",
          "avatarUrl" : "https://avatars2.githubusercontent.com/u/60356447?u=f6cdfccc6ea4254bd7c212099bbac2c27a00a28c&v=4"
        },
        "body" : "Done.",
        "createdAt" : "2020-07-06T14:36:00Z",
        "updatedAt" : "2020-07-06T14:36:00Z",
        "lastEditedBy" : {
          "login" : "SamirTalwar-DA",
          "name" : "Samir Talwar",
          "avatarUrl" : "https://avatars2.githubusercontent.com/u/60356447?u=f6cdfccc6ea4254bd7c212099bbac2c27a00a28c&v=4"
        },
        "tags" : [
          {
            "value" : "outdated"
          }
        ]
      }
    ],
    "commit" : "4347243c5df4d484e4a2fbcbd63028211da9da6d",
    "line" : null,
    "diffHunk" : "@@ -0,0 +1,20 @@\n+// Copyright (c) 2020 Digital Asset (Switzerland) GmbH and/or its affiliates. All rights reserved.\n+// SPDX-License-Identifier: Apache-2.0\n+\n+package com.daml.ledger.participant.state.kvutils.tools\n+\n+import scala.io.AnsiColor\n+\n+object Print {"
  }
]