[
  {
    "id" : "6e20ba15-1991-4c04-89de-c1dbb38f8699",
    "prId" : 2642,
    "comments" : [
      {
        "id" : "e0604ba3-2c2d-4691-a5e0-eb035028e44d",
        "parentId" : null,
        "author" : {
          "login" : "cocreature",
          "name" : "Moritz Kiefer",
          "avatarUrl" : "https://avatars1.githubusercontent.com/u/1313584?u=7864421488a876940b33e865c4b0091925617ca7&v=4"
        },
        "body" : "I’ll upstream this fix. The sdist tarball is also missing this file (which shows how many people tried to use `grpc-haskell` from Hackage :slightly_smiling_face:)",
        "createdAt" : "2019-08-23T07:05:35Z",
        "updatedAt" : "2019-08-23T11:47:53Z",
        "lastEditedBy" : {
          "login" : "cocreature",
          "name" : "Moritz Kiefer",
          "avatarUrl" : "https://avatars1.githubusercontent.com/u/1313584?u=7864421488a876940b33e865c4b0091925617ca7&v=4"
        },
        "tags" : [
        ]
      }
    ],
    "commit" : "c58c457c91219b4aa38c7297e5456fb27a62db51",
    "line" : 9,
    "diffHunk" : "@@ -1,1 +7,11 @@ build-type:          Simple\n cabal-version:       >=1.10\n+extra-source-files:  include/grpc_haskell.h\n \n Flag Debug"
  }
]